[
    {
        "id": 1,
        "address": "123 Main St",
        "phone": "555-0123",
        "rating": 4.5,
        "Area": "Anna Nagar",
        "City": "Chennai",
        "nofOrders": {
         "2024-12-26": 12,
         "2024-12-25": 31,
         "2024-12-24": 53,
         "2024-12-23": 14,
         "2024-12-22": 25,
         "2024-12-21": 36,
         "2024-12-20": 47,
         "2024-12-19": 58,
         "2024-12-18": 69,
         "2024-12-17": 10,
         "2024-12-16": 11,
         "2024-12-15": 12,
         "2024-12-14": 13,
         "2024-12-13": 14,
         "2024-12-12": 15
        },
        "location": ["13.0827", "80.2707"],
        "stocks": [
            {
                "productId": 1,
                "quantity": 100,
                "price": 100
            },
            {
                "productId": 2,
                "quantity": 500,
                "price": 100
            },
            {
                "productId": 3,
                "quantity": 300,
                "price": 100
            }
        ]
    },
    {
        "id": 2,
        "address": "456 Park Road",
        "phone": "555-0124",
        "rating": 4.8,
        "Area": "T Nagar",
        "City": "Chennai",
        "location": ["13.0418", "80.2341"],
        "stocks": [
            {
                "productId": 1,
                "quantity": 150,
                "price": 110
            },
            {
                "productId": 2,
                "quantity": 400,
                "price": 95
            }
        ],
        "nofOrders": {
            "2024-12-26": 15,
            "2024-12-25": 28,
            "2024-12-24": 42,
            "2024-12-23": 19,
            "2024-12-22": 33,
            "2024-12-21": 27,
            "2024-12-20": 45,
            "2024-12-19": 51,
            "2024-12-18": 38,
            "2024-12-17": 22,
            "2024-12-16": 29,
            "2024-12-15": 35,
            "2024-12-14": 41,
            "2024-12-13": 26,
            "2024-12-12": 31
        }
    },
    {
        "id": 3,
        "address": "789 Lake View",
        "phone": "555-0125",
        "rating": 4.2,
        "Area": "Velachery",
        "City": "Chennai",
        "location": ["12.9815", "80.2180"],
        "stocks": [
            {
                "productId": 1,
                "quantity": 200,
                "price": 105
            },
            {
                "productId": 3,
                "quantity": 250,
                "price": 98
            }
        ],
        "nofOrders": {
            "2024-12-26": 20,
            "2024-12-25": 35,
            "2024-12-24": 45,
            "2024-12-23": 25,
            "2024-12-22": 30,
            "2024-12-21": 40,
            "2024-12-20": 50,
            "2024-12-19": 45,
            "2024-12-18": 35,
            "2024-12-17": 30,
            "2024-12-16": 25,
            "2024-12-15": 40,
            "2024-12-14": 45,
            "2024-12-13": 35,
            "2024-12-12": 30
        }
    },
    {
        "id": 4,
        "address": "321 Beach Road",
        "phone": "555-0126",
        "rating": 4.6,
        "Area": "Adyar",
        "City": "Chennai",
        "location": ["13.0012", "80.2565"],
        "stocks": [
            {
                "productId": 2,
                "quantity": 300,
                "price": 102
            },
            {
                "productId": 3,
                "quantity": 400,
                "price": 97
            }
        ],
        "nofOrders": {
            "2024-12-26": 18,
            "2024-12-25": 32,
            "2024-12-24": 47,
            "2024-12-23": 23,
            "2024-12-22": 38,
            "2024-12-21": 42,
            "2024-12-20": 55,
            "2024-12-19": 48,
            "2024-12-18": 33,
            "2024-12-17": 27,
            "2024-12-16": 35,
            "2024-12-15": 43,
            "2024-12-14": 39,
            "2024-12-13": 28,
            "2024-12-12": 34
        }
    },
    {
        "id": 5,
        "address": "567 Temple Street",
        "phone": "555-0127",
        "rating": 4.3,
        "Area": "Mylapore",
        "City": "Chennai",
        "location": ["13.0369", "80.2676"],
        "stocks": [
            {
                "productId": 1,
                "quantity": 250,
                "price": 98
            },
            {
                "productId": 2,
                "quantity": 350,
                "price": 103
            }
        ],
        "nofOrders": {
            "2024-12-26": 25,
            "2024-12-25": 40,
            "2024-12-24": 50,
            "2024-12-23": 30,
            "2024-12-22": 35,
            "2024-12-21": 45,
            "2024-12-20": 55,
            "2024-12-19": 50,
            "2024-12-18": 40,
            "2024-12-17": 35,
            "2024-12-16": 30,
            "2024-12-15": 45,
            "2024-12-14": 50,
            "2024-12-13": 40,
            "2024-12-12": 35
        }
    },
    {
        "id": 6,
        "address": "890 Market Lane",
        "phone": "555-0128",
        "rating": 4.7,
        "Area": "Nungambakkam",
        "City": "Chennai",
        "location": ["13.0569", "80.2425"],
        "stocks": [
            {
                "productId": 1,
                "quantity": 180,
                "price": 107
            },
            {
                "productId": 3,
                "quantity": 280,
                "price": 99
            }
        ],
        "nofOrders": {
            "2024-12-26": 22,
            "2024-12-25": 37,
            "2024-12-24": 48,
            "2024-12-23": 28,
            "2024-12-22": 33,
            "2024-12-21": 43,
            "2024-12-20": 53,
            "2024-12-19": 47,
            "2024-12-18": 38,
            "2024-12-17": 32,
            "2024-12-16": 27,
            "2024-12-15": 42,
            "2024-12-14": 48,
            "2024-12-13": 37,
            "2024-12-12": 33
        }
    },
    {
        "id": 7,
        "address": "234 College Road",
        "phone": "555-0129",
        "rating": 4.4,
        "Area": "Guindy",
        "City": "Chennai",
        "location": ["13.0067", "80.2206"],
        "stocks": [
            {
                "productId": 2,
                "quantity": 220,
                "price": 101
            },
            {
                "productId": 3,
                "quantity": 320,
                "price": 96
            }
        ],
        "nofOrders": {
            "2024-12-26": 17,
            "2024-12-25": 30,
            "2024-12-24": 44,
            "2024-12-23": 21,
            "2024-12-22": 36,
            "2024-12-21": 40,
            "2024-12-20": 52,
            "2024-12-19": 46,
            "2024-12-18": 31,
            "2024-12-17": 25,
            "2024-12-16": 33,
            "2024-12-15": 41,
            "2024-12-14": 37,
            "2024-12-13": 26,
            "2024-12-12": 32
        }
    },
    {
        "id": 8,
        "address": "678 Railway Station Road",
        "phone": "555-0130",
        "rating": 4.9,
        "Area": "Egmore",
        "City": "Chennai",
        "location": ["13.0732", "80.2617"],
        "stocks": [
            {
                "productId": 1,
                "quantity": 270,
                "price": 104
            },
            {
                "productId": 2,
                "quantity": 370,
                "price": 99
            }
        ],
        "nofOrders": {
            "2024-12-26": 28,
            "2024-12-25": 43,
            "2024-12-24": 53,
            "2024-12-23": 33,
            "2024-12-22": 38,
            "2024-12-21": 48,
            "2024-12-20": 58,
            "2024-12-19": 53,
            "2024-12-18": 43,
            "2024-12-17": 38,
            "2024-12-16": 33,
            "2024-12-15": 48,
            "2024-12-14": 53,
            "2024-12-13": 43,
            "2024-12-12": 38
        }
    },
    {
        "id": 9,
        "address": "901 Garden Street",
        "phone": "555-0131",
        "rating": 4.1,
        "Area": "Kodambakkam",
        "City": "Chennai",
        "location": ["13.0511", "80.2285"],
        "stocks": [
            {
                "productId": 2,
                "quantity": 190,
                "price": 106
            },
            {
                "productId": 3,
                "quantity": 290,
                "price": 98
            }
        ],
        "nofOrders": {
            "2024-12-26": 16,
            "2024-12-25": 29,
            "2024-12-24": 43,
            "2024-12-23": 20,
            "2024-12-22": 35,
            "2024-12-21": 39,
            "2024-12-20": 51,
            "2024-12-19": 45,
            "2024-12-18": 30,
            "2024-12-17": 24,
            "2024-12-16": 32,
            "2024-12-15": 40,
            "2024-12-14": 36,
            "2024-12-13": 25,
            "2024-12-12": 31
        }
    },
    {
        "id": 10,
        "address": "432 Mall Road",
        "phone": "555-0132",
        "rating": 4.5,
        "Area": "Porur",
        "City": "Chennai",
        "location": ["13.0374", "80.1571"],
        "stocks": [
            {
                "productId": 1,
                "quantity": 230,
                "price": 103
            },
            {
                "productId": 3,
                "quantity": 330,
                "price": 97
            }
        ],
        "nofOrders": {
            "2024-12-26": 19,
            "2024-12-25": 34,
            "2024-12-24": 46,
            "2024-12-23": 24,
            "2024-12-22": 37,
            "2024-12-21": 41,
            "2024-12-20": 54,
            "2024-12-19": 49,
            "2024-12-18": 32,
            "2024-12-17": 26,
            "2024-12-16": 34,
            "2024-12-15": 42,
            "2024-12-14": 38,
            "2024-12-13": 27,
            "2024-12-12": 33
        }
    }
]